arcee/__init__.py
arcee/generator/__init__.py
arcee/generator/lexer_generator.py
arcee/generator/parser_generator.py
arcee/generator/token_generator.py
arcee/lexer/__init__.py
arcee/lexer/lexer.py
arcee/parser/__init__.py
arcee/parser/arcee_parser.py
arcee/utils/fn.py
arcee-0.1.1.dist-info/METADATA
arcee-0.1.1.dist-info/RECORD
arcee-0.1.1.dist-info/WHEEL
arcee-0.1.1.dist-info/entry_points.txt
arcee-0.1.1.dist-info/top_level.txt
test/__init__.py
test/integration_test.py
test/generator/__init__.py
test/generator/test_lexer_generator.py
test/generator/test_parser_generator.py
test/generator/test_token_generator.py
test/lexer/__init__.py
test/lexer/test_lexer.py
test/parser/__init__.py
test/parser/test_arcee_parser.py
