Metadata-Version: 2.1
Name: arcee
Version: 0.1.1
Summary: LL(1) parser generator
Home-page: https://github.com/tdkihrr/arcee
Author: tdkihrr
Author-email: huanghezhao@outlook.com
License: MIT
Keywords: parser-generator
Platform: any
Requires-Python: >=3.4.0
